MemReader/__init__.py
memreader-0.0.1.dist-info/METADATA
memreader-0.0.1.dist-info/WHEEL
memreader-0.0.1.dist-info/top_level.txt
memreader-0.0.1.dist-info/RECORD
