Metadata-Version: 2.4
Name: memreader
Version: 0.0.1
Summary: Read memory from dialogues.
Requires-Python: >=3.8
